<?xml version="1.0" encoding="UTF-8"?>

<databaseChangeLog
        xmlns="http://www.liquibase.org/xml/ns/dbchangelog"
        xmlns:xsi="http://www.w3.org/2001/XMLSchema-instance"
        xmlns:ext="http://www.liquibase.org/xml/ns/dbchangelog-ext"
        xsi:schemaLocation="http://www.liquibase.org/xml/ns/dbchangelog http://www.liquibase.org/xml/ns/dbchangelog/dbchangelog-3.8.xsd
        http://www.liquibase.org/xml/ns/dbchangelog-ext http://www.liquibase.org/xml/ns/dbchangelog/dbchangelog-ext.xsd">

    <changeSet id="Leonard99" author="Trinh Van Dat">
        <createTable tableName="user">

            <column name="id" type="INT" autoIncrement="true">
                <constraints primaryKey="true" primaryKeyName="user_pk"/>
            </column>

            <column name="name" type="VARCHAR(100)"/>

            <column name="address" type="VARCHAR(100)"/>

        </createTable>
    </changeSet>

</databaseChangeLog>